{
   "frames" : [
      {
         "filename" : "Background1",
         "frame" : {
            "h" : 989,
            "w" : 1472,
            "x" : 8,
            "y" : 8
         }
      },
      {
         "filename" : "Dirt Block",
         "frame" : {
            "h" : 64,
            "w" : 64,
            "x" : 8,
            "y" : 1005
         }
      },
      {
         "filename" : "Enemy1-1",
         "frame" : {
            "h" : 64,
            "w" : 64,
            "x" : 80,
            "y" : 1005
         }
      },
      {
         "filename" : "Enemy1-2",
         "frame" : {
            "h" : 64,
            "w" : 64,
            "x" : 152,
            "y" : 1005
         }
      },
      {
         "filename" : "Enemy1-3",
         "frame" : {
            "h" : 64,
            "w" : 64,
            "x" : 224,
            "y" : 1005
         }
      },
      {
         "filename" : "Grass Block",
         "frame" : {
            "h" : 64,
            "w" : 64,
            "x" : 296,
            "y" : 1005
         }
      },
      {
         "filename" : "House",
         "frame" : {
            "h" : 64,
            "w" : 64,
            "x" : 368,
            "y" : 1005
         }
      },
      {
         "filename" : "Item Empty",
         "frame" : {
            "h" : 64,
            "w" : 64,
            "x" : 8,
            "y" : 1077
         }
      },
      {
         "filename" : "Item",
         "frame" : {
            "h" : 64,
            "w" : 64,
            "x" : 80,
            "y" : 1077
         }
      },
      {
         "filename" : "NPC Move1",
         "frame" : {
            "h" : 64,
            "w" : 64,
            "x" : 152,
            "y" : 1077
         }
      },
      {
         "filename" : "NPC Move2",
         "frame" : {
            "h" : 64,
            "w" : 64,
            "x" : 440,
            "y" : 1005
         }
      },
      {
         "filename" : "NPC Move3",
         "frame" : {
            "h" : 64,
            "w" : 64,
            "x" : 224,
            "y" : 1077
         }
      },
      {
         "filename" : "NPC",
         "frame" : {
            "h" : 64,
            "w" : 64,
            "x" : 296,
            "y" : 1077
         }
      },
      {
         "filename" : "Teleporter1",
         "frame" : {
            "h" : 64,
            "w" : 64,
            "x" : 512,
            "y" : 1005
         }
      },
      {
         "filename" : "Teleporter2",
         "frame" : {
            "h" : 64,
            "w" : 64,
            "x" : 368,
            "y" : 1077
         }
      },
      {
         "filename" : "Teleporter3",
         "frame" : {
            "h" : 64,
            "w" : 64,
            "x" : 8,
            "y" : 1149
         }
      },
      {
         "filename" : "Teleporter4",
         "frame" : {
            "h" : 64,
            "w" : 64,
            "x" : 80,
            "y" : 1149
         }
      },
      {
         "filename" : "Tree Bottom1",
         "frame" : {
            "h" : 64,
            "w" : 64,
            "x" : 152,
            "y" : 1149
         }
      },
      {
         "filename" : "Tree Bottom2",
         "frame" : {
            "h" : 64,
            "w" : 64,
            "x" : 584,
            "y" : 1005
         }
      },
      {
         "filename" : "Tree Bottom3",
         "frame" : {
            "h" : 64,
            "w" : 64,
            "x" : 440,
            "y" : 1077
         }
      },
      {
         "filename" : "Tree Bottom4",
         "frame" : {
            "h" : 64,
            "w" : 64,
            "x" : 224,
            "y" : 1149
         }
      },
      {
         "filename" : "Tree Top1",
         "frame" : {
            "h" : 64,
            "w" : 64,
            "x" : 296,
            "y" : 1149
         }
      },
      {
         "filename" : "Tree Top2",
         "frame" : {
            "h" : 64,
            "w" : 64,
            "x" : 512,
            "y" : 1077
         }
      },
      {
         "filename" : "Tree Top3",
         "frame" : {
            "h" : 64,
            "w" : 64,
            "x" : 656,
            "y" : 1005
         }
      },
      {
         "filename" : "Tree Top4",
         "frame" : {
            "h" : 64,
            "w" : 64,
            "x" : 368,
            "y" : 1149
         }
      },
      {
         "filename" : "Water Block1",
         "frame" : {
            "h" : 64,
            "w" : 64,
            "x" : 8,
            "y" : 1221
         }
      },
      {
         "filename" : "Water Block2",
         "frame" : {
            "h" : 64,
            "w" : 64,
            "x" : 80,
            "y" : 1221
         }
      },
      {
         "filename" : "Water Block3",
         "frame" : {
            "h" : 64,
            "w" : 64,
            "x" : 584,
            "y" : 1077
         }
      },
      {
         "filename" : "Water Bottom1",
         "frame" : {
            "h" : 64,
            "w" : 64,
            "x" : 440,
            "y" : 1149
         }
      },
      {
         "filename" : "Water Bottom2",
         "frame" : {
            "h" : 64,
            "w" : 64,
            "x" : 152,
            "y" : 1221
         }
      },
      {
         "filename" : "Water Bottom3",
         "frame" : {
            "h" : 64,
            "w" : 64,
            "x" : 728,
            "y" : 1005
         }
      },
      {
         "filename" : "Platform-L",
         "frame" : {
            "h" : 27,
            "w" : 64,
            "x" : 224,
            "y" : 1221
         }
      },
      {
         "filename" : "Platform-M",
         "frame" : {
            "h" : 27,
            "w" : 64,
            "x" : 296,
            "y" : 1221
         }
      },
      {
         "filename" : "Platform-R",
         "frame" : {
            "h" : 27,
            "w" : 64,
            "x" : 512,
            "y" : 1149
         }
      },
      {
         "filename" : "Spikes",
         "frame" : {
            "h" : 25,
            "w" : 64,
            "x" : 656,
            "y" : 1077
         }
      },
      {
         "filename" : "Enemy3-1",
         "frame" : {
            "h" : 63,
            "w" : 57,
            "x" : 368,
            "y" : 1221
         }
      },
      {
         "filename" : "Enemy3-2",
         "frame" : {
            "h" : 63,
            "w" : 57,
            "x" : 224,
            "y" : 1256
         }
      },
      {
         "filename" : "Enemy3-3",
         "frame" : {
            "h" : 63,
            "w" : 57,
            "x" : 800,
            "y" : 1005
         }
      },
      {
         "filename" : "Enemy3-4",
         "frame" : {
            "h" : 63,
            "w" : 57,
            "x" : 289,
            "y" : 1256
         }
      },
      {
         "filename" : "Enemy3-5",
         "frame" : {
            "h" : 63,
            "w" : 57,
            "x" : 584,
            "y" : 1149
         }
      },
      {
         "filename" : "Enemy3-6",
         "frame" : {
            "h" : 63,
            "w" : 57,
            "x" : 656,
            "y" : 1110
         }
      },
      {
         "filename" : "Wings",
         "frame" : {
            "h" : 13,
            "w" : 52,
            "x" : 512,
            "y" : 1184
         }
      },
      {
         "filename" : "Seed",
         "frame" : {
            "h" : 50,
            "w" : 48,
            "x" : 8,
            "y" : 1293
         }
      },
      {
         "filename" : "Millet",
         "frame" : {
            "h" : 55,
            "w" : 44,
            "x" : 64,
            "y" : 1293
         }
      },
      {
         "filename" : "Sprite",
         "frame" : {
            "h" : 63,
            "w" : 34,
            "x" : 433,
            "y" : 1221
         }
      },
      {
         "filename" : "Sprite Move1",
         "frame" : {
            "h" : 63,
            "w" : 34,
            "x" : 116,
            "y" : 1293
         }
      },
      {
         "filename" : "Sprite Move2",
         "frame" : {
            "h" : 63,
            "w" : 34,
            "x" : 728,
            "y" : 1077
         }
      },
      {
         "filename" : "Sprite Move3",
         "frame" : {
            "h" : 63,
            "w" : 34,
            "x" : 158,
            "y" : 1293
         }
      },
      {
         "filename" : "Egg",
         "frame" : {
            "h" : 48,
            "w" : 34,
            "x" : 512,
            "y" : 1205
         }
      }
   ]
}
